flair/__init__.py
flair/data.py
flair/data_fetcher.py
flair/file_utils.py
flair/inference_utils.py
flair/nn.py
flair/optim.py
flair/samplers.py
flair/tokenization.py
flair/training_utils.py
flair/datasets/__init__.py
flair/datasets/base.py
flair/datasets/biomedical.py
flair/datasets/conllu.py
flair/datasets/document_classification.py
flair/datasets/relation_extraction.py
flair/datasets/sequence_labeling.py
flair/datasets/text_image.py
flair/datasets/text_text.py
flair/datasets/treebanks.py
flair/embeddings/__init__.py
flair/embeddings/base.py
flair/embeddings/document.py
flair/embeddings/image.py
flair/embeddings/legacy.py
flair/embeddings/token.py
flair/hyperparameter/__init__.py
flair/hyperparameter/param_selection.py
flair/hyperparameter/parameter.py
flair/models/__init__.py
flair/models/language_model.py
flair/models/relation_extractor_model.py
flair/models/sequence_tagger_model.py
flair/models/similarity_learning_model.py
flair/models/tars_tagger_model.py
flair/models/text_classification_model.py
flair/models/text_regression_model.py
flair/trainers/__init__.py
flair/trainers/language_model_trainer.py
flair/trainers/trainer.py
flair/visual/__init__.py
flair/visual/activations.py
flair/visual/manifold.py
flair/visual/ner_html.py
flair/visual/training_curves.py
flair_82-0.8.2.dist-info/LICENSE
flair_82-0.8.2.dist-info/METADATA
flair_82-0.8.2.dist-info/WHEEL
flair_82-0.8.2.dist-info/top_level.txt
flair_82-0.8.2.dist-info/RECORD
