Metadata-Version: 2.1
Name: flair-82
Version: 0.8.2
Summary: A very simple framework for state-of-the-art NLP
Home-page: https://github.com/muellerzr/flair
Author: Alan Akbik
Author-email: alan.akbik@gmail.com
License: MIT
Platform: UNKNOWN
Requires-Python: >=3.6
License-File: LICENSE
Requires-Dist: python-dateutil (>=2.6.1)
Requires-Dist: torch (>=1.5.0)
Requires-Dist: gensim (<=3.8.3,>=3.4.0)
Requires-Dist: tqdm (>=4.26.0)
Requires-Dist: segtok (>=1.5.7)
Requires-Dist: matplotlib (>=2.2.3)
Requires-Dist: mpld3 (==0.3)
Requires-Dist: scikit-learn (>=0.21.3)
Requires-Dist: sqlitedict (>=1.6.0)
Requires-Dist: deprecated (>=1.2.4)
Requires-Dist: hyperopt (>=0.1.1)
Requires-Dist: transformers (>=4.0.0)
Requires-Dist: bpemb (>=0.3.2)
Requires-Dist: regex
Requires-Dist: tabulate
Requires-Dist: langdetect
Requires-Dist: lxml
Requires-Dist: ftfy
Requires-Dist: sentencepiece (==0.1.95)
Requires-Dist: konoha (<5.0.0,>=4.0.0)
Requires-Dist: janome
Requires-Dist: gdown (==3.12.2)
Requires-Dist: huggingface-hub
Requires-Dist: conllu (>=4.0)
Requires-Dist: more-itertools (~=8.8.0)
